{"id": 20, "name_it": "Il Segreto del Capitano", "name_en": "The Captain's Secret", "size": 8, "rooms": [[2, 2, 2, 2, 0, 0, 0, 0], [2, 2, 2, 0, 0, 0, 0, 0], [2, 2, 2, 2, 2, 0, 0, 0], [2, 2, 2, 2, 1, 1, 1, 0], [3, 3, 3, 3, 1, 1, 1, 0], [3, 3, 3, 3, 4, 4, 4, 4], [3, 3, 3, 3, 3, 4, 4, 4], [3, 3, 3, 4, 4, 4, 4, 4]], "room_defs": [{"id": 0, "key": "plancia", "it": "Plancia", "en": "Bridge", "color": "#b3d4e8"}, {"id": 1, "key": "cabina", "it": "Cabina", "en": "Cabin", "color": "#d7c3e8"}, {"id": 2, "key": "cambusa", "it": "Cambusa", "en": "Galley", "color": "#f2c9a8"}, {"id": 3, "key": "stiva", "it": "Stiva", "en": "Hold", "color": "#b8b3c9"}, {"id": 4, "key": "ponte", "it": "Ponte", "en": "Deck", "color": "#e6c893"}], "furniture": [{"r": 0, "c": 4, "asset": "sedia"}, {"r": 1, "c": 1, "asset": "cassa"}, {"r": 1, "c": 2, "asset": "cassa"}, {"r": 1, "c": 6, "asset": "timone"}, {"r": 2, "c": 0, "asset": "scaffale"}, {"r": 2, "c": 5, "asset": "sedia"}, {"r": 3, "c": 3, "asset": "sedia"}, {"r": 3, "c": 4, "asset": "scaffale"}, {"r": 3, "c": 5, "asset": "cuccetta"}, {"r": 4, "c": 3, "asset": "cassa"}, {"r": 4, "c": 7, "asset": "scaffale"}, {"r": 5, "c": 1, "asset": "rete"}, {"r": 5, "c": 2, "asset": "barile"}, {"r": 5, "c": 4, "asset": "sedia"}, {"r": 6, "c": 0, "asset": "rete"}, {"r": 6, "c": 7, "asset": "cassa"}, {"r": 7, "c": 1, "asset": "cassa"}, {"r": 7, "c": 5, "asset": "salvagente"}, {"r": 7, "c": 7, "asset": "corda"}], "suspects": [{"id": 0, "name": "Carla", "gender": "F"}, {"id": 1, "name": "Dario", "gender": "M"}, {"id": 2, "name": "Irene", "gender": "F"}, {"id": 3, "name": "Giada", "gender": "F"}, {"id": 4, "name": "Nino", "gender": "M"}, {"id": 5, "name": "Bruno", "gender": "M"}, {"id": 6, "name": "Elena", "gender": "F"}, {"id": 7, "name": "Anna", "gender": "F"}], "victim": 7, "murderer": 6, "clues": [{"suspect": 0, "victim": false, "it": "Carla era l'unica seduta su una sedia.", "en": "Carla was the only one sitting in a chair."}, {"suspect": 1, "victim": false, "it": "Dario era da solo in Cambusa.", "en": "Dario was alone in the Galley."}, {"suspect": 2, "victim": false, "it": "Irene era esattamente una riga a nord di Giada.", "en": "Irene was exactly one row north of Giada."}, {"suspect": 3, "victim": false, "it": "Giada era da sola in Cabina.", "en": "Giada was alone in the Cabin."}, {"suspect": 4, "victim": false, "it": "Nino era esattamente una riga a nord di Bruno.", "en": "Nino was exactly one row north of Bruno."}, {"suspect": 5, "victim": false, "it": "Bruno era a nord di Elena.", "en": "Bruno was north of Elena."}, {"suspect": 6, "victim": false, "it": "Elena era accanto a una sedia.", "en": "Elena was beside a chair."}, {"suspect": 7, "victim": true, "it": "LA VITTIMA. Era da sola con l'assassino.", "en": "The Victim. Was alone with the murderer."}], "solution": [[0, 4], [1, 0], [2, 7], [3, 6], [4, 1], [5, 5], [6, 3], [7, 2]], "seed": 20000, "attempt": 54}